nuclipy/__init__.py
nuclipy/__main__.py
nuclipy/banners.py
nuclipy/colors.py
nuclipy/helper.py
nuclipy/scanner.py
nuclipy/template.py
nuclipy/templates/airflow-configuration-exposure.yaml
nuclipy/templates/alibaba-canal-info-leak.yaml
nuclipy/templates/amazon-docker-config-disclosure.yaml
nuclipy/templates/ansible-config-disclosure.yaml
nuclipy/templates/apache-config.yaml
nuclipy/templates/awstats-config.yaml
nuclipy/templates/awstats-script.yaml
nuclipy/templates/circleci-config.yaml
nuclipy/templates/circleci-ssh-config.yaml
nuclipy/templates/cisco-network-config.yaml
nuclipy/templates/composer-config.yaml
nuclipy/templates/configuration-listing.yaml
nuclipy/templates/coremail-config-disclosure.yaml
nuclipy/templates/detect-drone-config.yaml
nuclipy/templates/docker-compose-config.yaml
nuclipy/templates/esmtprc-config.yaml
nuclipy/templates/exposed-authentication.asmx.yaml
nuclipy/templates/exposed-bitkeeper.yaml
nuclipy/templates/exposed-bzr.yaml
nuclipy/templates/exposed-darcs.yaml
nuclipy/templates/exposed-hg.yaml
nuclipy/templates/exposed-sharepoint-list.yaml
nuclipy/templates/exposed-svn.yaml
nuclipy/templates/exposed-vscode.yaml
nuclipy/templates/ftp-credentials-exposure.yaml
nuclipy/templates/git-config-nginxoffbyslash.yaml
nuclipy/templates/git-config.yaml
nuclipy/templates/gmail-api-client-secrets.yaml
nuclipy/templates/golang-metrics.yaml
nuclipy/templates/hikvision-info-leak.yaml
nuclipy/templates/honeywell-scada-config.yaml
nuclipy/templates/htpasswd-detection.yaml
nuclipy/templates/httpd-config.yaml
nuclipy/templates/javascript-env.yaml
nuclipy/templates/joomla-config-file.yaml
nuclipy/templates/kyan-network-credentials-disclosure.yaml
nuclipy/templates/laravel-env.yaml
nuclipy/templates/lvmeng-uts-disclosure.yaml
nuclipy/templates/magento-config.yaml
nuclipy/templates/nagios-status-page.yaml
nuclipy/templates/netrc.yaml
nuclipy/templates/nginx-config.yaml
nuclipy/templates/opcache-status-exposure.yaml
nuclipy-1.0.3.dist-info/LICENSE
nuclipy-1.0.3.dist-info/METADATA
nuclipy-1.0.3.dist-info/WHEEL
nuclipy-1.0.3.dist-info/top_level.txt
nuclipy-1.0.3.dist-info/RECORD
