Metadata-Version: 2.1
Name: nuclipy
Version: 1.0.3
Summary: A template based vulnerability scanner (Inspired by Nuclei Scanner)
Home-page: https://github.com/prasant-paudel/nuclipy
Author: Prasant Paudel
Author-email: prashant.paudel.555@gmail.com
License: UNKNOWN
Project-URL: Bug Tracker, https://github.com/prasant-paudel/nuclipy/issues
Platform: UNKNOWN
Classifier: Programming Language :: Python :: 3
Classifier: License :: OSI Approved :: MIT License
Classifier: Operating System :: OS Independent
Requires-Python: >=3.6
License-File: LICENSE
Requires-Dist: requests
Requires-Dist: PyYaml
Requires-Dist: argparse
